{
  "part": "Viola 1",
  "absoluteNumber": 61,
  "relativeNumber": 13,
  "soundEvents": [
    {
      "start": 0.01369863,
      "id": "01"
    },
    {
      "start": 0.027924132,
      "id": "02"
    },
    {
      "start": 0.071127504,
      "id": "03"
    },
    {
      "start": 0.13277135,
      "id": "04"
    },
    {
      "start": 0.17492098,
      "id": "05"
    },
    {
      "start": 0.19810327,
      "id": "06"
    },
    {
      "start": 0.21022129,
      "id": "07"
    },
    {
      "start": 0.21654375,
      "id": "08"
    },
    {
      "start": 0.2702845,
      "id": "09"
    },
    {
      "start": 0.29030558,
      "id": "10"
    },
    {
      "start": 0.3361433,
      "id": "11"
    },
    {
      "start": 0.34404638,
      "id": "12"
    },
    {
      "start": 0.36617494,
      "id": "13"
    },
    {
      "start": 0.47839832,
      "id": "14"
    },
    {
      "start": 0.5131718,
      "id": "15"
    },
    {
      "start": 0.540569,
      "id": "16"
    },
    {
      "start": 0.5553214,
      "id": "17"
    },
    {
      "start": 0.5706006,
      "id": "18"
    },
    {
      "start": 0.60800845,
      "id": "19"
    },
    {
      "start": 0.6195996,
      "id": "20"
    },
    {
      "start": 0.6285564,
      "id": "21"
    },
    {
      "start": 0.6390938,
      "id": "22"
    },
    {
      "start": 0.65648056,
      "id": "23"
    },
    {
      "start": 0.68914646,
      "id": "24"
    },
    {
      "start": 0.6965227,
      "id": "25"
    },
    {
      "start": 0.73024244,
      "id": "26"
    },
    {
      "start": 0.7334036,
      "id": "27"
    },
    {
      "start": 0.76659644,
      "id": "28"
    },
    {
      "start": 0.8087461,
      "id": "29"
    },
    {
      "start": 0.82033724,
      "id": "30"
    },
    {
      "start": 0.8377239,
      "id": "31"
    },
    {
      "start": 0.85721815,
      "id": "32"
    },
    {
      "start": 0.9562698,
      "id": "33"
    },
    {
      "start": 0.9710221,
      "id": "34"
    },
    {
      "start": 0.99789256,
      "id": "35"
    }
  ]
}