{
  "part": "bass",
  "absoluteNumber": 164,
  "relativeNumber": 8,
  "soundEvents": [
    {
      "start": 0.007853404,
      "id": "01"
    },
    {
      "start": 0.0790576,
      "id": "02"
    },
    {
      "start": 0.08848167,
      "id": "03"
    },
    {
      "start": 0.14397906,
      "id": "04"
    },
    {
      "start": 0.17068063,
      "id": "05"
    },
    {
      "start": 0.2329843,
      "id": "06"
    },
    {
      "start": 0.27591622,
      "id": "07"
    },
    {
      "start": 0.31151834,
      "id": "08"
    },
    {
      "start": 0.3209424,
      "id": "09"
    },
    {
      "start": 0.56911,
      "id": "10"
    },
    {
      "start": 0.6675393,
      "id": "11"
    },
    {
      "start": 0.6884817,
      "id": "12"
    },
    {
      "start": 0.6958115,
      "id": "13"
    },
    {
      "start": 0.8078534,
      "id": "14"
    },
    {
      "start": 0.8251309,
      "id": "15"
    },
    {
      "start": 0.87015707,
      "id": "16"
    },
    {
      "start": 0.9010471,
      "id": "17"
    }
  ]
}