{
  "part": "Violin 3",
  "absoluteNumber": 44,
  "relativeNumber": 12,
  "soundEvents": [
    {
      "start": 0.014752371,
      "id": "01"
    },
    {
      "start": 0.033719708,
      "id": "02"
    },
    {
      "start": 0.05110643,
      "id": "03"
    },
    {
      "start": 0.06533193,
      "id": "04"
    },
    {
      "start": 0.11327713,
      "id": "05"
    },
    {
      "start": 0.21601686,
      "id": "06"
    },
    {
      "start": 0.26817703,
      "id": "07"
    },
    {
      "start": 0.28029507,
      "id": "08"
    },
    {
      "start": 0.33350894,
      "id": "09"
    },
    {
      "start": 0.39567965,
      "id": "10"
    },
    {
      "start": 0.47418335,
      "id": "11"
    },
    {
      "start": 0.5300316,
      "id": "12"
    },
    {
      "start": 0.630137,
      "id": "13"
    },
    {
      "start": 0.6348788,
      "id": "14"
    },
    {
      "start": 0.69336147,
      "id": "15"
    },
    {
      "start": 0.74183357,
      "id": "16"
    },
    {
      "start": 0.84615386,
      "id": "17"
    },
    {
      "start": 0.923077,
      "id": "18"
    },
    {
      "start": 0.9778715,
      "id": "19"
    },
    {
      "start": 0.9894626,
      "id": "20"
    }
  ]
}